
        <page string="Timesheets" attrs="{'invisible': [('project_id', '=', False)]}" modifiers="{'invisible':[['project_id','=',false]]}">
            <group modifiers="{}">
                <group modifiers="{}">
                    <field name="planned_hours" widget="float_time" on_change="1" modifiers="{}"/>
                </group>
                <group modifiers="{}">
                    <field name="progress" widget="progressbar" modifiers="{'readonly':true}"/>
                </group>
            </group>
            <field name="timesheet_ids" mode="tree,kanban" context="{'default_project_id': project_id}" on_change="1" modifiers="{}"/>
            <group modifiers="{}">
                <group class="oe_subtotal_footer oe_right" name="project_hours" modifiers="{}">
                    <field name="effective_hours" widget="float_time" on_change="1" modifiers="{}"/>
                    <field name="children_hours" widget="float_time" attrs="{'invisible' : [('children_hours', '=', 0.0)]}" on_change="1" modifiers="{'invisible':[['children_hours','=',0]],'readonly':true}"/>
                    <field name="total_hours_spent" widget="float_time" class="oe_subtotal_footer_separator" attrs="{'invisible' : [('children_hours', '=', 0.0)]}" modifiers="{'invisible':[['children_hours','=',0]],'readonly':true}"/>
                    <field name="remaining_hours" widget="float_time" class="oe_subtotal_footer_separator" readonly="1" modifiers="{'readonly':true}"/>
                </group>
            </group>
        </page>